gcdb/__init__.py
gcdb-0.1.3.dist-info/METADATA
gcdb-0.1.3.dist-info/RECORD
gcdb-0.1.3.dist-info/WHEEL
gcdb-0.1.3.dist-info/entry_points.txt
gcdb-0.1.3.dist-info/top_level.txt
