Metadata-Version: 2.1
Name: gcdb
Version: 0.1.3
Summary: # Generate Compilation Database
Requires-Dist: Click
